DCMT4Lib/__init__.py
DCMT4Lib/CommonTools/CommonDefine.py
DCMT4Lib/CommonTools/DCMT4WrapperBase.py
DCMT4Lib/CommonTools/DataAssignHelper.py
DCMT4Lib/CommonTools/DataStructure.py
DCMT4Lib/CommonTools/EnumDefine.py
DCMT4Lib/CommonTools/__init__.py
DCMT4Lib/MT4Funs/AccountInformationFuns.py
DCMT4Lib/MT4Funs/ChartOperationsFuns.py
DCMT4Lib/MT4Funs/CheckupFuns.py
DCMT4Lib/MT4Funs/ConversionFuns.py
DCMT4Lib/MT4Funs/DateAndTimeFuns.py
DCMT4Lib/MT4Funs/MT4FunsBase.py
DCMT4Lib/MT4Funs/MarketInfoFuns.py
DCMT4Lib/MT4Funs/ObjectFuns.py
DCMT4Lib/MT4Funs/PredefinedVariablesFuns.py
DCMT4Lib/MT4Funs/TechnicalIndicatorsFuns.py
DCMT4Lib/MT4Funs/TestFuns.py
DCMT4Lib/MT4Funs/TradeFuns.py
DCMT4Lib/MT4Funs/__init__.py
DCMT4Lib-0.0.2.dist-info/LICENSE
DCMT4Lib-0.0.2.dist-info/METADATA
DCMT4Lib-0.0.2.dist-info/WHEEL
DCMT4Lib-0.0.2.dist-info/top_level.txt
DCMT4Lib-0.0.2.dist-info/RECORD
